Workbook

Sheet Supuestos
A1: GEINSTAL - Modelo de Rentabilidad por Cliente
A2: Mantenimiento Integral de Edificios
A4: DATOS DE EMPRESA
A5: Empleados totales | B5: 305
A6: Facturación total (€) | B6: 35000000
A7: Coste medio técnico (€/año) | B7: 35000
A9: SUPUESTOS POR CLIENTE
A10: Cliente | B10: Ingresos Anuales (€) | C10: Técnicos Asignados | D10: Coste Técnico (€/año) | E10: Coste Personal Total (€/año) | F10: Material Estimado (€/año) | G10: Coste Directo Total (€/año) | H10: % Horas Extra Urgencias | I10: Coste Urgencias (€/año)
A11: Hospital Vall d'Hebron | B11: 450000 | C11: 8 | D11: 35000 | E11: =C11*D11 -> 280000 | F11: 45000 | G11: =E11+F11 -> 325000 | H11: 0.08 | I11: =E11*H11 -> 22400
A12: SEAT Martorell | B12: 280000 | C12: 4 | D12: 35000 | E12: =C12*D12 -> 140000 | F12: 30000 | G12: =E12+F12 -> 170000 | H12: 0.15 | I12: =E12*H12 -> 21000
A13: UAB Bellaterra | B13: 180000 | C13: 3 | D13: 35000 | E13: =C13*D13 -> 105000 | F13: 15000 | G13: =E13+F13 -> 120000 | H13: 0.03 | I13: =E13*H13 -> 3150
A14: Danone Parets | B14: 120000 | C14: 2 | D14: 35000 | E14: =C14*D14 -> 70000 | F14: 10000 | G14: =E14+F14 -> 80000 | H14: 0.05 | I14: =E14*H14 -> 3500
A15: CCCB Barcelona | B15: 95000 | C15: 1 | D15: 35000 | E15: =C15*D15 -> 35000 | F15: 8000 | G15: =E15+F15 -> 43000 | H15: 0.02 | I15: =E15*H15 -> 700
A16: TOTAL | B16: =SUM(B11:B15) -> 1125000 | C16: =SUM(C11:C15) -> 18 | E16: =SUM(E11:E15) -> 630000 | F16: =SUM(F11:F15) -> 108000 | G16: =SUM(G11:G15) -> 738000 | I16: =SUM(I11:I15) -> 50750
A18: PARÁMETROS GENERALES
A19: % Gastos estructura s/ingresos | B19: 0.12
A20: % Gastos comerciales s/ingresos | B20: 0.05
A21: % Otros gastos indirectos s/ingresos | B21: 0.03
A22: % Total gastos indirectos | B22: =B19+B20+B21 -> 0.2
A24: NOTAS
A25: • Valores en azul son inputs modificables (hardcoded)
A26: • Los gastos indirectos se asignan proporcionalmente a los ingresos de cada cliente
A27: • El coste de personal incluye salario bruto + SS empresa (coste empresa total)

Sheet Modelo
A1: GEINSTAL - Análisis de Rentabilidad por Cliente (Mensual)
A2: Todos los valores en €/mes. Fórmulas vinculadas a pestaña Supuestos.
A4: INGRESOS MENSUALES
A5: Cliente | B5: Vall d'Hebron | C5: SEAT | D5: UAB | E5: Danone | F5: CCCB | G5: TOTAL
A6: Ingresos contrato | B6: =Supuestos!B11/12 -> 37500 | C6: =Supuestos!B12/12 -> 23333.333 | D6: =Supuestos!B13/12 -> 15000 | E6: =Supuestos!B14/12 -> 10000 | F6: =Supuestos!B15/12 -> 7916.6667 | G6: =SUM(B6:F6) -> 93750
A8: COSTES DIRECTOS MENSUALES
A9: Coste personal | B9: =Supuestos!E11/12 -> 23333.333 | C9: =Supuestos!E12/12 -> 11666.667 | D9: =Supuestos!E13/12 -> 8750 | E9: =Supuestos!E14/12 -> 5833.3333 | F9: =Supuestos!E15/12 -> 2916.6667 | G9: =SUM(B9:F9) -> 52500
A10: Coste material | B10: =Supuestos!F11/12 -> 3750 | C10: =Supuestos!F12/12 -> 2500 | D10: =Supuestos!F13/12 -> 1250 | E10: =Supuestos!F14/12 -> 833.33333 | F10: =Supuestos!F15/12 -> 666.66667 | G10: =SUM(B10:F10) -> 9000
A11: Coste urgencias | B11: =Supuestos!I11/12 -> 1866.6667 | C11: =Supuestos!I12/12 -> 1750 | D11: =Supuestos!I13/12 -> 262.5 | E11: =Supuestos!I14/12 -> 291.66667 | F11: =Supuestos!I15/12 -> 58.333333 | G11: =SUM(B11:F11) -> 4229.1667
A12: Total costes directos | B12: =B9+B10+B11 -> 28950 | C12: =C9+C10+C11 -> 15916.667 | D12: =D9+D10+D11 -> 10262.5 | E12: =E9+E10+E11 -> 6958.3333 | F12: =F9+F10+F11 -> 3641.6667 | G12: =SUM(B12:F12) -> 65729.167
A14: MARGEN BRUTO
A15: Margen bruto (€) | B15: =B6-B12 -> 8550 | C15: =C6-C12 -> 7416.6667 | D15: =D6-D12 -> 4737.5 | E15: =E6-E12 -> 3041.6667 | F15: =F6-F12 -> 4275 | G15: =SUM(B15:F15) -> 28020.833
A16: Margen bruto (%) | B16: =IF(B6=0,0,B15/B6) -> 0.228 | C16: =IF(C6=0,0,C15/C6) -> 0.31785714 | D16: =IF(D6=0,0,D15/D6) -> 0.31583333 | E16: =IF(E6=0,0,E15/E6) -> 0.30416667 | F16: =IF(F6=0,0,F15/F6) -> 0.54 | G16: =IF(G6=0,0,G15/G6) -> 0.29888889
A18: COSTES INDIRECTOS ASIGNADOS
A19: Gastos estructura | B19: =B6*Supuestos!$B$19 -> 4500 | C19: =C6*Supuestos!$B$19 -> 2800 | D19: =D6*Supuestos!$B$19 -> 1800 | E19: =E6*Supuestos!$B$19 -> 1200 | F19: =F6*Supuestos!$B$19 -> 950 | G19: =SUM(B19:F19) -> 11250
A20: Gastos comerciales | B20: =B6*Supuestos!$B$20 -> 1875 | C20: =C6*Supuestos!$B$20 -> 1166.6667 | D20: =D6*Supuestos!$B$20 -> 750 | E20: =E6*Supuestos!$B$20 -> 500 | F20: =F6*Supuestos!$B$20 -> 395.83333 | G20: =SUM(B20:F20) -> 4687.5
A21: Otros gastos indirectos | B21: =B6*Supuestos!$B$21 -> 1125 | C21: =C6*Supuestos!$B$21 -> 700 | D21: =D6*Supuestos!$B$21 -> 450 | E21: =E6*Supuestos!$B$21 -> 300 | F21: =F6*Supuestos!$B$21 -> 237.5 | G21: =SUM(B21:F21) -> 2812.5
A22: Total costes indirectos | B22: =B19+B20+B21 -> 7500 | C22: =C19+C20+C21 -> 4666.6667 | D22: =D19+D20+D21 -> 3000 | E22: =E19+E20+E21 -> 2000 | F22: =F19+F20+F21 -> 1583.3333 | G22: =SUM(B22:F22) -> 18750
A24: MARGEN NETO
A25: Margen neto (€) | B25: =B15-B22 -> 1050 | C25: =C15-C22 -> 2750 | D25: =D15-D22 -> 1737.5 | E25: =E15-E22 -> 1041.6667 | F25: =F15-F22 -> 2691.6667 | G25: =SUM(B25:F25) -> 9270.8333
A26: Margen neto (%) | B26: =IF(B6=0,0,B25/B6) -> 0.028 | C26: =IF(C6=0,0,C25/C6) -> 0.11785714 | D26: =IF(D6=0,0,D25/D6) -> 0.11583333 | E26: =IF(E6=0,0,E25/E6) -> 0.10416667 | F26: =IF(F6=0,0,F25/F6) -> 0.34 | G26: =IF(G6=0,0,G25/G6) -> 0.098888889
A28: CHECK DE CUADRE
A29: Concepto | B29: Modelo (mensual) | C29: Supuestos (anual/12) | D29: Diferencia | E29: Estado
A30: Ingresos totales | B30: =G6 -> 93750 | C30: =Supuestos!B16/12 -> 93750 | D30: =B30-C30 -> 0 | E30: =IF(ABS(D30)<0.01,"✅ OK","❌ ERROR") -> ✅ OK
A31: Costes directos totales (incl. urgencias) | B31: =G12 -> 65729.167 | C31: =(Supuestos!G16+Supuestos!I16)/12 -> 65729.167 | D31: =B31-C31 -> 0 | E31: =IF(ABS(D31)<0.01,"✅ OK","❌ ERROR") -> ✅ OK
A32: Margen neto = Ingresos - CD - CI | B32: =G25 -> 9270.8333 | C32: =G6-G12-G22 -> 9270.8333 | D32: =B32-C32 -> 0 | E32: =IF(ABS(D32)<0.01,"✅ OK","❌ ERROR") -> ✅ OK
A33: % Indirectos aplicado | B33: =IF(G6=0,0,G22/G6) -> 0.2 | C33: =Supuestos!B22 -> 0.2 | D33: =B33-C33 -> 0 | E33: =IF(ABS(D33)<0.0001,"✅ OK","❌ ERROR") -> ✅ OK
B35: Vall d'Hebron | C35: SEAT | D35: UAB | E35: Danone | F35: CCCB
A36: Margen Bruto % | B36: =B16 -> 0.228 | C36: =C16 -> 0.31785714 | D36: =D16 -> 0.31583333 | E36: =E16 -> 0.30416667 | F36: =F16 -> 0.54
A37: Margen Neto % (sin urgencias) | B37: =IF(B6=0,0,(B6-(B9+B10)-B22)/B6) -> 0.077777778 | C37: =IF(C6=0,0,(C6-(C9+C10)-C22)/C6) -> 0.19285714 | D37: =IF(D6=0,0,(D6-(D9+D10)-D22)/D6) -> 0.13333333 | E37: =IF(E6=0,0,(E6-(E9+E10)-E22)/E6) -> 0.13333333 | F37: =IF(F6=0,0,(F6-(F9+F10)-F22)/F6) -> 0.34736842
A38: Margen Neto Ajustado % | B38: =B26 -> 0.028 | C38: =C26 -> 0.11785714 | D38: =D26 -> 0.11583333 | E38: =E26 -> 0.10416667 | F38: =F26 -> 0.34
